vl_utility_test/__init__.py
vl_utility_test/arithmetic.py
vl_utility_test/greet.py
vl_utility_test/utility_module.py
vl_utility_test-0.1.dist-info/LICENSE
vl_utility_test-0.1.dist-info/METADATA
vl_utility_test-0.1.dist-info/WHEEL
vl_utility_test-0.1.dist-info/top_level.txt
vl_utility_test-0.1.dist-info/RECORD
