Metadata-Version: 2.1
Name: vl-utility-test
Version: 0.1
Summary: For creating raster tiles and merging
Home-page: https://github.com/pkumarvassar/vl_utility_test.git
Author: Praveen Kumar
Author-email: pkumar@vassarlabs.com
License: UNKNOWN
Platform: UNKNOWN
Classifier: Programming Language :: Python :: 3
Classifier: Operating System :: OS Independent
Requires-Python: >=3.8
License-File: LICENSE
